LICENSE
MANIFEST.in
README.rst
setup.py
django_treensl.egg-info/PKG-INFO
django_treensl.egg-info/SOURCES.txt
django_treensl.egg-info/dependency_links.txt
django_treensl.egg-info/top_level.txt
docs/treensl_params_py
treensl/__init__.py
treensl/admin.py
treensl/calc_values.py
treensl/models.py
treensl/tests.py
treensl/views.py
treensl/migrations/0001_initial.py
treensl/migrations/__init__.py
treensl/sql_scripts/ini_postgres.sql
treensl/sql_scripts/templ_sql_postgres_for_new_tables.sql