Metadata-Version: 1.1
Name: django-treensl
Version: 0.2.3
Summary: Django application to the tree structure in the model.
Home-page: https://github.com/EvgeniyBurdin/django_treensl
Author: Evgeniy Burdin
Author-email: e.s.burdin@mail.ru
License: BSD License
Keywords: django
Platform: UNKNOWN
Classifier: Environment :: Web Environment
Classifier: Framework :: Django
Classifier: Intended Audience :: Developers
Classifier: Operating System :: OS Independent
Classifier: Programming Language :: Python
Classifier: Programming Language :: Python :: 2
Classifier: Programming Language :: Python :: 2.7
Classifier: Programming Language :: Python :: 3
Classifier: Programming Language :: Python :: 3.4
Classifier: Programming Language :: Python :: 3.5
